CHANGELOG.rst
LICENSE.txt
MANIFEST.in
README.rst
TODO.rst
VERSION.txt
setup.cfg
setup.py
test-requirements.txt
doc/manual.rst
pyramid_jitt/__init__.py
pyramid_jitt/controller.py
pyramid_jitt/engine.py
pyramid_jitt/test.py
pyramid_jitt.egg-info/PKG-INFO
pyramid_jitt.egg-info/SOURCES.txt
pyramid_jitt.egg-info/dependency_links.txt
pyramid_jitt.egg-info/requires.txt
pyramid_jitt.egg-info/top_level.txt
pyramid_jitt.egg-info/zip-safe
pyramid_jitt/res/jittloader-jquery.js
pyramid_jitt/res/jittloader.html