Metadata-Version: 1.1
Name: pyramid-jitt
Version: 0.1.2
Summary: A Just-In-Time compilation and packaging of JavaScript templates for Pyramid.
Home-page: http://github.com/canaryhealth/pyramid_jitt
Author: Philip J Grabner, Canary Health Inc
Author-email: oss@canary.md
License: MIT (http://opensource.org/licenses/MIT)
Keywords: web wsgi pyramid tween javascript compiler packager
Platform: UNKNOWN
Classifier: Development Status :: 3 - Alpha
Classifier: Intended Audience :: Developers
Classifier: Programming Language :: Python
Classifier: Framework :: Pyramid
Classifier: Environment :: Console
Classifier: Environment :: Web Environment
Classifier: Operating System :: OS Independent
Classifier: Topic :: Internet
Classifier: Topic :: Software Development
Classifier: Topic :: Internet :: WWW/HTTP
Classifier: Topic :: Internet :: WWW/HTTP :: WSGI
Classifier: Topic :: Software Development :: Libraries :: Application Frameworks
Classifier: Natural Language :: English
Classifier: License :: OSI Approved :: MIT License
Classifier: License :: Public Domain
